{"header":"Date Stacked","description":"<p>Abbreviated month stacked on top of numerical day of the month.</p>\n","deprecated":false,"experimental":false,"reference":"Simple.Date Stacked","referenceNumber":"3.5","referenceURI":"simple-date-stacked","weight":0,"colors":[],"markup":"templates/components/date-stacked/date-stacked.twig","source":{"filename":"node_modules/decanter/core/src/scss/components/date-stacked/_date-stacked.scss","line":3},"depth":2,"modifiers":[{"name":".su-date-stacked--no-background","description":"Black type on transparent background","className":"su-date-stacked--no-background"}],"parameters":[],"source_twig":"templates/components/date-stacked/date-stacked.twig"}